create_rl_app/__init__.py
create_rl_app/_vendored/.gitkeep
create_rl_app/_vendored/__init__.py
create_rl_app/_vendored/jaxnasium/.vendor_info
create_rl_app/_vendored/jaxnasium/.vendor_version
create_rl_app/_vendored/jaxnasium/algorithms/__init__.py
create_rl_app/_vendored/jaxnasium/algorithms/_algorithm.py
create_rl_app/_vendored/jaxnasium/algorithms/_dqn.py
create_rl_app/_vendored/jaxnasium/algorithms/_ppo.py
create_rl_app/_vendored/jaxnasium/algorithms/_pqn.py
create_rl_app/_vendored/jaxnasium/algorithms/_sac.py
create_rl_app/_vendored/jaxnasium/algorithms/networks/__init__.py
create_rl_app/_vendored/jaxnasium/algorithms/networks/_agent_networks.py
create_rl_app/_vendored/jaxnasium/algorithms/networks/_architectures.py
create_rl_app/_vendored/jaxnasium/algorithms/networks/_input_output.py
create_rl_app/cli.py
create_rl_app/resources/__init__.py
create_rl_app/resources/env_template.py
create_rl_app/resources/train_template.py
create_rl_app-0.0.7.dist-info/WHEEL
create_rl_app-0.0.7.dist-info/entry_points.txt
create_rl_app-0.0.7.dist-info/METADATA
create_rl_app-0.0.7.dist-info/RECORD
