Metadata-Version: 2.3
Name: create-rl-app
Version: 0.0.7
Summary: Bootstrap a new Reinforcement Learning project
Author: Koen Ponse
Author-email: Koen Ponse <k.ponse@liacs.leidenuniv.nl>
Requires-Python: >=3.11
